app/__init__.py
app/application.py
app/handlers/__init__.py
app/handlers/download_data.py
app/services/__init__.py
app/services/data.py
mango_cli-0.3.9.dist-info/METADATA
mango_cli-0.3.9.dist-info/WHEEL
mango_cli-0.3.9.dist-info/entry_points.txt
mango_cli-0.3.9.dist-info/top_level.txt
mango_cli-0.3.9.dist-info/RECORD
