Metadata-Version: 2.1
Name: mango-cli
Version: 0.3.9
Summary: Mangosoft CLI
Home-page: UNKNOWN
Author: Mangosoft
Author-email: wilson.mendoza@mango-soft.com
License: UNKNOWN
Platform: UNKNOWN
Requires-Dist: bleach (==6.0.0)
Requires-Dist: blessed (==1.20.0)
Requires-Dist: boto3 (==1.26.127)
Requires-Dist: botocore (==1.29.127)
Requires-Dist: bump2version (==1.0.1)
Requires-Dist: certifi (==2022.12.7)
Requires-Dist: charset-normalizer (==3.1.0)
Requires-Dist: click (==8.1.3)
Requires-Dist: docutils (==0.19)
Requires-Dist: et-xmlfile (==1.1.0)
Requires-Dist: idna (==3.4)
Requires-Dist: importlib-metadata (==6.6.0)
Requires-Dist: inquirer (==3.1.3)
Requires-Dist: jaraco.classes (==3.2.3)
Requires-Dist: jmespath (==1.0.1)
Requires-Dist: keyring (==23.13.1)
Requires-Dist: markdown-it-py (==2.2.0)
Requires-Dist: mdurl (==0.1.2)
Requires-Dist: more-itertools (==9.1.0)
Requires-Dist: numpy (==1.24.3)
Requires-Dist: openpyxl (==3.1.2)
Requires-Dist: pandas (==2.0.1)
Requires-Dist: pkginfo (==1.9.6)
Requires-Dist: pyfiglet (==0.8.post1)
Requires-Dist: Pygments (==2.15.1)
Requires-Dist: python-dateutil (==2.8.2)
Requires-Dist: python-editor (==1.0.4)
Requires-Dist: pytz (==2023.3)
Requires-Dist: readchar (==4.0.5)
Requires-Dist: readme-renderer (==37.3)
Requires-Dist: requests (==2.30.0)
Requires-Dist: requests-toolbelt (==1.0.0)
Requires-Dist: rfc3986 (==2.0.0)
Requires-Dist: rich (==13.3.5)
Requires-Dist: s3transfer (==0.6.1)
Requires-Dist: six (==1.16.0)
Requires-Dist: twine (==4.0.2)
Requires-Dist: tzdata (==2023.3)
Requires-Dist: urllib3 (==1.26.15)
Requires-Dist: wcwidth (==0.2.6)
Requires-Dist: webencodings (==0.5.1)
Requires-Dist: wheel (==0.40.0)
Requires-Dist: zipp (==3.15.0)
